pycodata/__init__.py
pycodata/constants_2010.cpython-313-darwin.so
pycodata/constants_2014.cpython-313-darwin.so
pycodata/constants_2018.cpython-313-darwin.so
pycodata/constants_2022.cpython-313-darwin.so
pycodata/libcodata.a
pycodata/libcodata.dylib
pycodata/version.cpython-313-darwin.so
pycodata-2.3.0.dist-info/licenses/LICENSE
pycodata-2.3.0.dist-info/METADATA
pycodata-2.3.0.dist-info/WHEEL
pycodata-2.3.0.dist-info/top_level.txt
pycodata-2.3.0.dist-info/RECORD
