Metadata-Version: 2.4
Name: pycodata
Version: 2.3.0
Summary: pycodata: CODATA constants for python.
Author-email: Milan Skocic <milan.skocic@gmail.com>
License-Expression: MIT
Project-URL: Documentation, https://milanskocic.github.io/codata/index.html
Project-URL: Source, https://github.com/MilanSkocic/codata
Classifier: Development Status :: 5 - Production/Stable
Classifier: Intended Audience :: Science/Research
Requires-Python: >=3.9
License-File: LICENSE
Dynamic: license-file
